geezram
