Metadata-Version: 2.1
Name: geezram
Version: 0.0.1
Summary: geezram - Telegram MTProto API Client Library for Python.
Home-page: https://github.com/geezram/geezram
Author: geezram
Author-email: berliansayang1503@gmail.com
License: GNU Lesser General Public License v3.0 (LGPL-3.0)
Project-URL: Bug Tracker, https://github.com/geezram/geezram/issues
Project-URL: Documentation, https://geezram.tech
Project-URL: Source Code, https://github.com/geezram/geezram
Platform: UNKNOWN
Classifier: Programming Language :: Python
Classifier: Programming Language :: Python :: 3
Classifier: Programming Language :: Python :: 3.7
Classifier: Programming Language :: Python :: 3.8
Classifier: Programming Language :: Python :: 3.9
Classifier: Programming Language :: Python :: 3.10
Classifier: Programming Language :: Python :: 3.11
Classifier: Programming Language :: Python :: Implementation
Classifier: Programming Language :: Python :: Implementation :: CPython
Classifier: Programming Language :: Python :: Implementation :: PyPy
Classifier: License :: OSI Approved :: GNU General Public License v3 (GPLv3)
Classifier: Operating System :: OS Independent
Requires-Python: ~=3.7
License-File: LICENSE
License-File: NOTICE
Requires-Dist: Pillow (==8.3.2)
Requires-Dist: aiosqlite (<0.18.0,>=0.16.0)
Requires-Dist: motor (==3.0.0)
Requires-Dist: pyaes (==1.6.1)
Requires-Dist: pymediainfo (==6.0.1)
Requires-Dist: pymongo (==4.4.1)
Requires-Dist: pysocks (==1.7.1)
Requires-Dist: requests
